neutronbraggedge/__init__.py
neutronbraggedge/braggedge.py
neutronbraggedge/config.cfg
neutronbraggedge/config.py
neutronbraggedge/constants.py
neutronbraggedge/utilities.py
neutronbraggedge/braggedges_handler/__init__.py
neutronbraggedge/braggedges_handler/braggedge_calculator.py
neutronbraggedge/braggedges_handler/structure_handler.py
neutronbraggedge/data/__init__.py
neutronbraggedge/data/full_material_list.dat
neutronbraggedge/data/material_list.dat
neutronbraggedge/experiment_handler/__init__.py
neutronbraggedge/experiment_handler/experiment.py
neutronbraggedge/experiment_handler/lambda_wavelength.py
neutronbraggedge/experiment_handler/tof.py
neutronbraggedge/lattice_handler/__init__.py
neutronbraggedge/lattice_handler/lattice.py
neutronbraggedge/material_handler/__init__.py
neutronbraggedge/material_handler/retrieve_material_metadata.py
neutronbraggedge/material_handler/retrieve_metadata_table.py
neutronbraggedge-2.0.6.data/data/neutronbraggedge/config.cfg
python/__init__.py
tests/neutronbraggedge/__init__.py
tests/neutronbraggedge/braggedge_test.py
tests/neutronbraggedge/signon.py
tests/neutronbraggedge/utilities_test.py
tests/neutronbraggedge/braggedge_handler/__init__.py
tests/neutronbraggedge/braggedge_handler/braggedge_calculator_test.py
tests/neutronbraggedge/braggedge_handler/structure_handler_test.py
tests/neutronbraggedge/experiment_handler/__init__.py
tests/neutronbraggedge/experiment_handler/experiment_test.py
tests/neutronbraggedge/experiment_handler/lambda_test.py
tests/neutronbraggedge/experiment_handler/tof_test.py
tests/neutronbraggedge/lattice_handler/__init__.py
tests/neutronbraggedge/lattice_handler/lattice_test.py
tests/neutronbraggedge/material_handler/__init__.py
tests/neutronbraggedge/material_handler/retrieve_material_metadata_test.py
tests/neutronbraggedge/material_handler/retrieve_metadata_table_test.py
neutronbraggedge-2.0.6.dist-info/METADATA
neutronbraggedge-2.0.6.dist-info/WHEEL
neutronbraggedge-2.0.6.dist-info/top_level.txt
neutronbraggedge-2.0.6.dist-info/RECORD
