Metadata-Version: 2.1
Name: neutronbraggedge
Version: 2.0.6
Summary: Bragg Edge work at the SNS
Home-page: https://github.com/ornlneutronimaging/BraggEdge
Author: Jean Bilheux
Author-email: bilheuxjm@ornl.gov
License: BSD
Keywords: neutron imaging bragg edge
Platform: UNKNOWN
Classifier: Development Status :: 3 - Alpha
Classifier: Topic :: Scientific/Engineering :: Physics
Classifier: Intended Audience :: Developers
Classifier: Programming Language :: Python :: 3.5
Classifier: Programming Language :: Python :: 3.6
Requires-Dist: numpy
Requires-Dist: configparser
Requires-Dist: pandas
Requires-Dist: lxml
Requires-Dist: html5lib
Requires-Dist: beautifulsoup4
